{"cameraMode":{"drawMode":0,"name":"Shaded","section":"Shading Mode"},"sceneLighting":true,"audioPlay":false,"sceneViewState":{"m_AlwaysRefresh":false,"showFog":true,"showSkybox":true,"showFlares":true,"showImageEffects":true,"showParticleSystems":true,"showVisualEffectGraphs":true,"m_FxEnabled":true},"in2DMode":false,"pivot":{"x":0.1424577832221985,"y":4.304609775543213,"z":13.603137016296387},"rotation":{"x":-0.013807571493089199,"y":0.015595443546772004,"z":-0.0002149127540178597,"w":-0.9997919201850891},"size":10.960335731506348,"orthographic":false}